LRS_Lulav/LRS_Bag.py
LRS_Lulav/LRS_agent.py
LRS_Lulav/LRS_com.py
LRS_Lulav/LRS_manager.py
LRS_Lulav/LRS_params.py
LRS_Lulav/LRS_util.py
LRS_Lulav/__init__.py
LRS_Lulav/create_robot.py
LRS_Lulav/modules/LulavBagAnalyzer.py
LRS_Lulav/modules/__init__.py
LRS_Lulav/modules/automatic_simulator_runner.py
LRS_Lulav/modules/ros_runner.py
LRS_Lulav/modules/sim_runner.py
LRS_Lulav/modules/start_ros.py
LRS_Lulav-0.2.2.dist-info/LICENSE
LRS_Lulav-0.2.2.dist-info/METADATA
LRS_Lulav-0.2.2.dist-info/WHEEL
LRS_Lulav-0.2.2.dist-info/top_level.txt
LRS_Lulav-0.2.2.dist-info/RECORD
