Metadata-Version: 2.1
Name: LRS-Lulav
Version: 0.2.2
Summary: LRS_Lulav 
Home-page: http://pypi.python.org/pypi/LRS/
Author: vovacooper
Author-email: vova@lulav.com
License: LICENSE.txt
License-File: LICENSE
Requires-Dist: Django (>=1.1.1)
Requires-Dist: pytest
Requires-Dist: pymongo
Requires-Dist: pysqlite3
Requires-Dist: redis
Requires-Dist: soupsieve
Requires-Dist: bs4
